abilian/__init__.py
abilian/app.py
abilian/config.py
abilian/extensions.py
abilian/i18n.py
abilian/wsgi.py
abilian/cli/__init__.py
abilian/cli/base.py
abilian/cli/indexing.py
abilian/core/__init__.py
abilian/core/entities.py
abilian/core/logger_patch.py
abilian/core/plugin_manager.py
abilian/core/service_manager.py
abilian/core/signals.py
abilian/core/singleton.py
abilian/core/util.py
abilian/core/dramatiq/__init__.py
abilian/core/dramatiq/cli.py
abilian/core/dramatiq/scheduler.py
abilian/core/dramatiq/setup.py
abilian/core/dramatiq/singleton.py
abilian/core/extensions/__init__.py
abilian/core/extensions/csrf.py
abilian/core/extensions/jinjaext.py
abilian/core/extensions/login.py
abilian/core/extensions/mail.py
abilian/core/extensions/redis.py
abilian/core/extensions/sqlalchemy.py
abilian/core/extensions/upstream_info.py
abilian/core/models/__init__.py
abilian/core/models/attachment.py
abilian/core/models/base.py
abilian/core/models/base_mixin.py
abilian/core/models/blob.py
abilian/core/models/comment.py
abilian/core/models/owned.py
abilian/core/models/subjects.py
abilian/core/models/tag.py
abilian/core/sqlalchemy/__init__.py
abilian/core/sqlalchemy/extension.py
abilian/core/sqlalchemy/listeners.py
abilian/core/sqlalchemy/types.py
abilian/lib/__init__.py
abilian/lib/scanner.py
abilian/sbe/__init__.py
abilian/sbe/app.py
abilian/sbe/extension.py
abilian/sbe/apps/__init__.py
abilian/sbe/apps/calendar/__init__.py
abilian/sbe/apps/calendar/actions.py
abilian/sbe/apps/calendar/forms.py
abilian/sbe/apps/calendar/models.py
abilian/sbe/apps/calendar/views.py
abilian/sbe/apps/calendar/templates/calendar/_base.html
abilian/sbe/apps/calendar/templates/calendar/archives.html
abilian/sbe/apps/calendar/templates/calendar/event.html
abilian/sbe/apps/calendar/templates/calendar/index.html
abilian/sbe/apps/communities/__init__.py
abilian/sbe/apps/communities/actions.py
abilian/sbe/apps/communities/blueprint.py
abilian/sbe/apps/communities/common.py
abilian_sbe-1.1.15.dist-info/METADATA
abilian_sbe-1.1.15.dist-info/WHEEL
abilian_sbe-1.1.15.dist-info/licenses/LICENCE.txt
abilian_sbe-1.1.15.dist-info/RECORD
