Metadata-Version: 2.4
Name: abilian-sbe
Version: 1.1.15
Summary: Social Business platform (entreprise collaboration and information management)
Project-URL: Repository, https://github.com/abilian/abilian-sbe
Author-email: Abilian SAS <sales@abilian.com>
License-Expression: LGPL-2.0-or-later
License-File: LICENCE.txt
Requires-Python: <3.13,>=3.11
Requires-Dist: apscheduler<4.0.0,>=3.10.4
Requires-Dist: attrs>=24.2.0
Requires-Dist: babel
Requires-Dist: bcrypt
Requires-Dist: bleach[css]<7.0.0,>=6.2.0
Requires-Dist: blinker>=1.6.2
Requires-Dist: certifi
Requires-Dist: chardet
Requires-Dist: click>=8.1.3
Requires-Dist: closure==20161201
Requires-Dist: cssmin
Requires-Dist: defusedxml<0.8.0,>=0.7.1
Requires-Dist: deprecated
Requires-Dist: devtools
Requires-Dist: dramatiq-abort<2.0.0,>=1.1.0
Requires-Dist: dramatiq<2.0.0,>=1.15.0
Requires-Dist: filelock<4.0,>=3.15
Requires-Dist: flask-assets==2.1.0
Requires-Dist: flask-babel<1.1.0,>=1.0.0
Requires-Dist: flask-dramatiq<0.7.0,>=0.6.0
Requires-Dist: flask-login<0.7.0,>=0.6.3
Requires-Dist: flask-mail>=0.9.1
Requires-Dist: flask-migrate<4.1.0,>=4.0.5
Requires-Dist: flask-sqlalchemy==3.0.1
Requires-Dist: flask-super>=0.2.8
Requires-Dist: flask-talisman<1.2.0,>=1.1.0
Requires-Dist: flask-wtf==1.2.0
Requires-Dist: flask<3.1.0,>=3.0.2
Requires-Dist: gunicorn
Requires-Dist: html2text<2025,>=2024
Requires-Dist: hyperlink>=21.0.0
Requires-Dist: itsdangerous>=2.1.2
Requires-Dist: jinja2<3.2.0,>=3.1.3
Requires-Dist: jsmin
Requires-Dist: langid>=1.1.6
Requires-Dist: loguru<0.8.0,>=0.7.2
Requires-Dist: lxml
Requires-Dist: markdown<4,>=3
Requires-Dist: markupsafe<2.2.0,>=2.1.4
Requires-Dist: maxminddb
Requires-Dist: numpy<2.0.0,>=1.26.3
Requires-Dist: openpyxl
Requires-Dist: pandas>=2.2.0
Requires-Dist: pillow
Requires-Dist: psycopg2<3.0.0,>=2.9.9
Requires-Dist: pytest>=8.3.3
Requires-Dist: python-dateutil<3.0.0,>=2.8.2
Requires-Dist: python-dotenv>=1.0.1
Requires-Dist: python-magic
Requires-Dist: pytz
Requires-Dist: redis<5.0,>=4.6.0
Requires-Dist: sentry-sdk[flask]
Requires-Dist: sqlalchemy==1.4.35
Requires-Dist: svcs>=24.1.0
Requires-Dist: toolz
Requires-Dist: tqdm
Requires-Dist: validate-email
Requires-Dist: webassets==2.0
Requires-Dist: werkzeug<3.2,>=3.1.0
Requires-Dist: whoosh-reloaded<3.0.0,>=2.7.5
Requires-Dist: wtforms-alchemy==0.18.0
Requires-Dist: wtforms-sqlalchemy<0.5.0,>=0.4.1
Requires-Dist: wtforms==3.1.2
Requires-Dist: xlwt
